[
  {
    "id": "mow.DE-NW-EU-SE091-20210823-109-000",
    "version": 1,
    "startDate": "2021-11-09T15:17:17+01:00",
    "severity": "Minor",
    "type": "Update",
    "i18nTitle": {
      "de": "+++ Betretungsverbot Bergschadensgebiet Stadt Mechernich +++"
    },
    "transKeys": {
      "event": "BBK-EVC-059"
    }
  },
  {
    "id": "mow.DE-HH-HH-SE033-20230417-33-000",
    "version": 5,
    "startDate": "2023-04-17T19:56:45+02:00",
    "severity": "Minor",
    "type": "Alert",
    "i18nTitle": {
      "de": "Warnung vor Kontakt mit Wasser der Bille - Hamburg, Rothenburgsort, Bille bis Mündung in die Elbe"
    },
    "transKeys": {
      "event": "BBK-EVC-078"
    }
  },
  {
    "id": "mow.DE-NW-AC-SE090-20230530-90-000",
    "version": 5,
    "startDate": "2023-05-30T03:55:11+02:00",
    "severity": "Minor",
    "type": "Alert",
    "i18nTitle": {
      "de": "Rauchgase durch Vegetationsbrand - Monschau ; Roetgen"
    },
    "transKeys": {
      "event": "BBK-EVC-030"
    }
  },
  {
    "id": "mow.DE-NI-VER-W077-20230530-000",
    "version": 5,
    "startDate": "2023-05-30T06:18:12+02:00",
    "severity": "Minor",
    "type": "Alert",
    "i18nTitle": {
      "de": "Rauchentwicklung durch Gebäudebrand in Achim - Achim"
    },
    "transKeys": {
      "event": "BBK-EVC-034"
    }
  },
  {
    "id": "mow.DE-SH-OD-SE105-20230530-105-001",
    "version": 5,
    "startDate": "2023-05-30T09:48:03+02:00",
    "expiresDate": "2023-05-30T15:48:03+02:00",
    "severity": "Severe",
    "type": "Cancel",
    "i18nTitle": {
      "de": "Entwarnung: Allgemeiner Schadensfall - Lensahn"
    },
    "transKeys": {
      "event": "BBK-EVC-027"
    }
  },
  {
    "id": "mow.DE-TH-UH-W116-20230530-001",
    "version": 5,
    "startDate": "2023-05-30T10:05:03+02:00",
    "severity": "Minor",
    "type": "Update",
    "i18nTitle": {
      "de": "Rauchentwicklung in Bad Langensalza im Bereich Innenstadt - Stadtgebiet Bad Langensalza"
    },
    "transKeys": {
      "event": "BBK-EVC-078"
    }
  }
]
