[
  {
    "id": "mow.DE-NW-EU-SE091-20210823-109-000",
    "version": 1,
    "startDate": "2021-11-09T15:17:17+01:00",
    "severity": "Minor",
    "type": "Update",
    "i18nTitle": {
      "de": "+++ Betretungsverbot Bergschadensgebiet Stadt Mechernich +++"
    },
    "transKeys": {
      "event": "BBK-EVC-059"
    }
  },
  {
    "id": "mow.DE-HH-HH-SE033-20230417-33-000",
    "version": 5,
    "startDate": "2023-04-17T19:56:45+02:00",
    "severity": "Minor",
    "type": "Alert",
    "i18nTitle": {
      "de": "Warnung vor Kontakt mit Wasser der Bille - Hamburg, Rothenburgsort, Bille bis Mündung in die Elbe"
    },
    "transKeys": {
      "event": "BBK-EVC-078"
    }
  },
  {
    "id": "mow.DE-RP-TR-SE004-20230524-4-003",
    "version": 5,
    "startDate": "2023-05-24T13:15:56+02:00",
    "expiresDate": "2023-05-24T19:15:56+02:00",
    "severity": "Severe",
    "type": "Cancel",
    "i18nTitle": {
      "de": "Entwarnung: Großbrand Industriegebiet Flugplatz Bitburg - Bitburg"
    },
    "transKeys": {
      "event": "BBK-EVC-010"
    }
  },
  {
    "id": "mow.DE-HE-KS-SE106-20230524-106-001",
    "version": 5,
    "startDate": "2023-05-24T13:23:35+02:00",
    "expiresDate": "2023-05-24T19:23:35+02:00",
    "severity": "Severe",
    "type": "Cancel",
    "i18nTitle": {
      "de": "Entwarnung: Großbrand - Ginsheim-Gustavsburg"
    },
    "transKeys": {
      "event": "BBK-EVC-034"
    }
  },
  {
    "id": "mow.DE-RP-KO-SE113-20230524-113-002",
    "version": 5,
    "startDate": "2023-05-24T16:52:48+02:00",
    "severity": "Minor",
    "type": "Alert",
    "i18nTitle": {
      "de": "Fund / Entschärfung einer Weltkriegsbombe - Koblenz Rauental"
    },
    "transKeys": {
      "event": "BBK-EVC-079"
    }
  },
  {
    "id": "mow.DE-BW-RT-SE050-20230524-50-000",
    "version": 5,
    "startDate": "2023-05-24T18:22:49+02:00",
    "expiresDate": "2023-05-25T00:22:49+02:00",
    "severity": "Minor",
    "type": "Cancel",
    "i18nTitle": {
      "de": "Entwarnung: Trinkwasserabkochgebot für die Ortsteile Eschelbach und Obersöllbach - Neuenstein-Eschelbach und Neuenstein-Obersöllbach"
    },
    "transKeys": {
      "event": "BBK-EVC-069"
    }
  }
]
